SoftwareDesignAndImplementationLectureNotesWashingtonCse331/README.md
SoftwareDesignAndImplementationLectureNotesWashingtonCse331/__init__.py
SoftwareDesignAndImplementationLectureNotesWashingtonCse331/__main__.py
SoftwareDesignAndImplementationLectureNotesWashingtonCse331/file.epub
SoftwareDesignAndImplementationLectureNotesWashingtonCse331/index.html
SoftwareDesignAndImplementationLectureNotesWashingtonCse331/css/__init__.py
SoftwareDesignAndImplementationLectureNotesWashingtonCse331/css/annotations.css
SoftwareDesignAndImplementationLectureNotesWashingtonCse331/css/main.css
SoftwareDesignAndImplementationLectureNotesWashingtonCse331/css/normalize.css
SoftwareDesignAndImplementationLectureNotesWashingtonCse331/css/popup.css
SoftwareDesignAndImplementationLectureNotesWashingtonCse331/font/__init__.py
SoftwareDesignAndImplementationLectureNotesWashingtonCse331/font/fontello.eot
SoftwareDesignAndImplementationLectureNotesWashingtonCse331/font/fontello.svg
SoftwareDesignAndImplementationLectureNotesWashingtonCse331/font/fontello.ttf
SoftwareDesignAndImplementationLectureNotesWashingtonCse331/font/fontello.woff
SoftwareDesignAndImplementationLectureNotesWashingtonCse331/img/__init__.py
SoftwareDesignAndImplementationLectureNotesWashingtonCse331/img/annotator-glyph-sprite.png
SoftwareDesignAndImplementationLectureNotesWashingtonCse331/img/annotator-icon-sprite.png
SoftwareDesignAndImplementationLectureNotesWashingtonCse331/img/apple-touch-icon.png
SoftwareDesignAndImplementationLectureNotesWashingtonCse331/img/cancelfullscreen.png
SoftwareDesignAndImplementationLectureNotesWashingtonCse331/img/close.png
SoftwareDesignAndImplementationLectureNotesWashingtonCse331/img/fullscreen.png
SoftwareDesignAndImplementationLectureNotesWashingtonCse331/img/loader.gif
SoftwareDesignAndImplementationLectureNotesWashingtonCse331/img/menu-icon.png
SoftwareDesignAndImplementationLectureNotesWashingtonCse331/img/save.png
software_design_and_implementation_lecture_notes_washington_cse331-2024.3.2.0.dist-info/METADATA
software_design_and_implementation_lecture_notes_washington_cse331-2024.3.2.0.dist-info/WHEEL
software_design_and_implementation_lecture_notes_washington_cse331-2024.3.2.0.dist-info/entry_points.txt
software_design_and_implementation_lecture_notes_washington_cse331-2024.3.2.0.dist-info/top_level.txt
software_design_and_implementation_lecture_notes_washington_cse331-2024.3.2.0.dist-info/RECORD
